devart/mongodb/__init__.py
devart/mongodb/mongodb.cpython-313-x86_64-linux-gnu.so
devart/mongodb/mongodb.pyi
devart/mongodb/sqlalchemy/__init__.py
devart_mongodb_connector-1.2.0.dist-info/LICENSE.txt
devart_mongodb_connector-1.2.0.dist-info/METADATA
devart_mongodb_connector-1.2.0.dist-info/WHEEL
devart_mongodb_connector-1.2.0.dist-info/top_level.txt
devart_mongodb_connector-1.2.0.dist-info/RECORD
