Metadata-Version: 2.1
Name: devart-mongodb-connector
Version: 1.2.0
Summary: New level of functionality and performance in data access via Python
Home-page: https://devart.com
Author: Devart
Author-email: support@devart.com
License: Other/Proprietary License
Project-URL: Homepage, https://devart.com/python/mongodb/
Project-URL: Download, https://devart.com/python/mongodb/download.html
Project-URL: History, https://devart.com/python/mongodb/revision_history.html
Project-URL: License, https://www.devart.com/python/eula.html
Project-URL: Documentation, https://docs.devart.com/python/mongodb/overview.htm
Requires-Python: >=3.7
License-File: LICENSE.txt
